comment_format/__init__.py
comment_format/comment_format.py
comment_format/lang_c.py
comment_format/lang_cpp.py
comment_format/utils.py
comment_format-0.1.3.dist-info/LICENSE
comment_format-0.1.3.dist-info/METADATA
comment_format-0.1.3.dist-info/WHEEL
comment_format-0.1.3.dist-info/entry_points.txt
comment_format-0.1.3.dist-info/top_level.txt
comment_format-0.1.3.dist-info/RECORD
