Metadata-Version: 2.2
Name: comment_format
Version: 0.1.3
Summary: A tool to check code comment format
Author-email: Alex Fabre <m.alexfabre@gmail.com>
License: MIT License
Project-URL: Homepage, https://github.com/AlexFabre/comment-format
Project-URL: Issues, https://github.com/AlexFabre/comment-format/issues
Classifier: Programming Language :: Python :: 3
Classifier: Operating System :: OS Independent
Requires-Python: >=3.10
License-File: LICENSE
Requires-Dist: codespell
